blob_creator/__init__.py
blob_creator/const.py
blob_creator/core.py
blob_creator/functions.py
blob_creator/uploader.py
blob_creator-3.2.5.dist-info/LICENSE
blob_creator-3.2.5.dist-info/METADATA
blob_creator-3.2.5.dist-info/WHEEL
blob_creator-3.2.5.dist-info/top_level.txt
blob_creator-3.2.5.dist-info/RECORD
