Metadata-Version: 2.1
Name: blob-creator
Version: 3.2.5
Summary: Package to create dummy datasets for analysis tasks
Home-page: https://github.com/mckoh/blob_creator
Author: Michael Kohlegger
Author-email: michael@datenberge.org
License: UNKNOWN
Project-URL: Bug Tracker, https://github.com/mckoh/blob_creator/issues
Platform: UNKNOWN
Classifier: Programming Language :: Python :: 3
Classifier: License :: OSI Approved :: MIT License
Classifier: Operating System :: OS Independent
Requires-Python: >=3.6
Requires-Dist: pytest
Requires-Dist: openpyxl
Requires-Dist: pandas
Requires-Dist: numpy
Requires-Dist: matplotlib
Requires-Dist: Pillow
Requires-Dist: names
Requires-Dist: svglib
Requires-Dist: reportlab
Requires-Dist: pyocclient
Requires-Dist: requests
